azure/mgmt/core/__init__.py
azure/mgmt/core/_async_pipeline_client.py
azure/mgmt/core/_pipeline_client.py
azure/mgmt/core/_version.py
azure/mgmt/core/exceptions.py
azure/mgmt/core/py.typed
azure/mgmt/core/tools.py
azure/mgmt/core/policies/__init__.py
azure/mgmt/core/policies/_authentication.py
azure/mgmt/core/policies/_authentication_async.py
azure/mgmt/core/policies/_base.py
azure/mgmt/core/policies/_base_async.py
azure/mgmt/core/polling/__init__.py
azure/mgmt/core/polling/arm_polling.py
azure/mgmt/core/polling/async_arm_polling.py
azure_mgmt_core-1.4.0.dist-info/LICENSE
azure_mgmt_core-1.4.0.dist-info/LICENSE.md
azure_mgmt_core-1.4.0.dist-info/METADATA
azure_mgmt_core-1.4.0.dist-info/WHEEL
azure_mgmt_core-1.4.0.dist-info/top_level.txt
azure_mgmt_core-1.4.0.dist-info/RECORD
