Metadata-Version: 2.1
Name: azure-mgmt-core
Version: 1.4.0
Summary: Microsoft Azure Management Core Library for Python
Home-page: https://github.com/Azure/azure-sdk-for-python/tree/main/sdk/core/azure-mgmt-core
Author: Microsoft Corporation
Author-email: azpysdkhelp@microsoft.com
License: MIT License
Classifier: Development Status :: 5 - Production/Stable
Classifier: Programming Language :: Python
Classifier: Programming Language :: Python :: 3 :: Only
Classifier: Programming Language :: Python :: 3
Classifier: Programming Language :: Python :: 3.7
Classifier: Programming Language :: Python :: 3.8
Classifier: Programming Language :: Python :: 3.9
Classifier: Programming Language :: Python :: 3.10
Classifier: Programming Language :: Python :: 3.11
Classifier: License :: OSI Approved :: MIT License
Requires-Python: >=3.7
License-File: LICENSE
License-File: LICENSE.md
